setup.py
MostWantedAnimals/__init__.py
MostWantedAnimals.egg-info/PKG-INFO
MostWantedAnimals.egg-info/SOURCES.txt
MostWantedAnimals.egg-info/dependency_links.txt
MostWantedAnimals.egg-info/not-zip-safe
MostWantedAnimals.egg-info/top_level.txt