Metadata-Version: 1.0
Name: MostWantedAnimals
Version: 0.1
Summary: Lame
Home-page: http://github.com/shankar-ray/Animals
Author: shankar-ray
Author-email: shankar.ray030@gmail.com
License: MIT
Platform: UNKNOWN
